AUTHORS
CHANGELOG.txt
LICENSE
MANIFEST.in
README.rst
setup.cfg
setup.py
cms/__init__.py
cms/api.py
cms/app_base.py
cms/apphook_pool.py
cms/appresolver.py
cms/apps.py
cms/cms_plugins.py
cms/cms_toolbar.py
cms/constants.py
cms/context_processors.py
cms/exceptions.py
cms/menu.py
cms/menu_bases.py
cms/plugin_base.py
cms/plugin_pool.py
cms/plugin_processors.py
cms/plugin_rendering.py
cms/toolbar_base.py
cms/toolbar_pool.py
cms/urls.py
cms/views.py
cms/admin/__init__.py
cms/admin/change_list.py
cms/admin/forms.py
cms/admin/pageadmin.py
cms/admin/permissionadmin.py
cms/admin/placeholderadmin.py
cms/admin/settingsadmin.py
cms/admin/static_placeholder.py
cms/admin/useradmin.py
cms/admin/views.py
cms/admin/dialog/__init__.py
cms/admin/dialog/forms.py
cms/admin/dialog/views.py
cms/cache/__init__.py
cms/cache/choices.py
cms/cache/page.py
cms/cache/permissions.py
cms/cache/placeholder.py
cms/extensions/__init__.py
cms/extensions/admin.py
cms/extensions/extension_pool.py
cms/extensions/models.py
cms/extensions/toolbar.py
cms/forms/__init__.py
cms/forms/fields.py
cms/forms/utils.py
cms/forms/widgets.py
cms/locale/af/LC_MESSAGES/django.mo
cms/locale/af/LC_MESSAGES/django.po
cms/locale/af/LC_MESSAGES/djangojs.mo
cms/locale/af/LC_MESSAGES/djangojs.po
cms/locale/ar/LC_MESSAGES/django.mo
cms/locale/ar/LC_MESSAGES/django.po
cms/locale/ar/LC_MESSAGES/djangojs.mo
cms/locale/ar/LC_MESSAGES/djangojs.po
cms/locale/be/LC_MESSAGES/django.mo
cms/locale/be/LC_MESSAGES/django.po
cms/locale/be/LC_MESSAGES/djangojs.mo
cms/locale/be/LC_MESSAGES/djangojs.po
cms/locale/bg/LC_MESSAGES/django.mo
cms/locale/bg/LC_MESSAGES/django.po
cms/locale/bg/LC_MESSAGES/djangojs.mo
cms/locale/bg/LC_MESSAGES/djangojs.po
cms/locale/bn/LC_MESSAGES/django.mo
cms/locale/bn/LC_MESSAGES/django.po
cms/locale/bn/LC_MESSAGES/djangojs.mo
cms/locale/bn/LC_MESSAGES/djangojs.po
cms/locale/ca/LC_MESSAGES/django.mo
cms/locale/ca/LC_MESSAGES/django.po
cms/locale/ca/LC_MESSAGES/djangojs.mo
cms/locale/ca/LC_MESSAGES/djangojs.po
tocka_django_cms.egg-info/PKG-INFO
tocka_django_cms.egg-info/SOURCES.txt
tocka_django_cms.egg-info/dependency_links.txt
tocka_django_cms.egg-info/not-zip-safe
tocka_django_cms.egg-info/pbr.json
tocka_django_cms.egg-info/requires.txt
tocka_django_cms.egg-info/top_level.txt